perception_dev_tools/__init__.py
perception_dev_tools/test.py
perception_dev_tools/viewer.py
perception_dev_tools-0.1.1.dist-info/METADATA
perception_dev_tools-0.1.1.dist-info/WHEEL
perception_dev_tools-0.1.1.dist-info/RECORD
