Metadata-Version: 2.1
Name: perception-dev-tools
Version: 0.1.1
Summary: 
Author: zhangshuaiqing
Author-email: zhangshuaiqing123@126.com
Requires-Python: >=3.8,<4.0
Classifier: Programming Language :: Python :: 3
Classifier: Programming Language :: Python :: 3.8
Classifier: Programming Language :: Python :: 3.9
Classifier: Programming Language :: Python :: 3.10
Classifier: Programming Language :: Python :: 3.11
Classifier: Programming Language :: Python :: 3.12
Classifier: Programming Language :: Python :: 3.13
Requires-Dist: fire (>=0.7.0,<0.8.0)
Requires-Dist: open3d (>=0.19.0,<0.20.0)
